{
    "@context": "https://w3id.org/codemeta/3.0",
    "@type": "SoftwareSourceCode",
    "name": "SLEPIAN_Echo",
    "programmingLanguage": [
        {
            "@type": "ComputerLanguage",
            "name": "Matlab"
        }
    ],
    "applicationCategory": "Modular",
    "operatingSystem": [
        "Unix",
        "Linux",
        "Mac OS",
        "Windows"
    ],
    "author": [
        {
            "@type": "Person",
            "givenName": "Alain",
            "familyName": "Plattner",
            "affiliation": {
                "@type": "Organization",
                "name": "Princeton University",
                "address": "Princeton, United States"
            },
            "email": "mailto:alainplattner@gmail.com"
        },
        {
            "@type": "Person",
            "givenName": "Frederik",
            "familyName": "Simons",
            "affiliation": {
                "@type": "Organization",
                "name": "Princeton University",
                "address": "Princeton, United States"
            },
            "email": "mailto:fjsimons@gmail.com"
        }
    ],
    "dateCreated": "2012-01-01",
    "keywords": [
        "Climate",
        "slepian",
        "computation",
        "harmonics",
        "functions",
        "doi",
        "routines pertaining",
        "paper published",
        "routines",
        "toolbox",
        "slepian echo",
        "Toolbox"
    ],
    "license": {
        "@type": "CreativeWork",
        "name": "GPL v2"
    },
    "description": "Routines pertaining to the paper published as: doi: 10.1016/j.acha.2012.12.001",
    "url": "https://csdms.colorado.edu/wiki/Model:SLEPIAN_Echo",
    "developmentStatus": "Active"
}