{
  "subject": "Gc2d#3002##",
  "data": [
    {
      "property": "Additional_city",
      "dataitem": [
        {
          "type": 2,
          "item": "Boulder"
        }
      ]
    },
    {
      "property": "Additional_country",
      "dataitem": [
        {
          "type": 2,
          "item": "United States"
        }
      ]
    },
    {
      "property": "Additional_email_address",
      "dataitem": [
        {
          "type": 5,
          "item": "mailto:huttone@colorado.edu"
        }
      ]
    },
    {
      "property": "Additional_first_name",
      "dataitem": [
        {
          "type": 2,
          "item": "Eric"
        }
      ]
    },
    {
      "property": "Additional_institute",
      "dataitem": [
        {
          "type": 2,
          "item": "CSDMS, INSTAAR, University of Colorado"
        }
      ]
    },
    {
      "property": "Additional_last_name",
      "dataitem": [
        {
          "type": 2,
          "item": "Hutton"
        }
      ]
    },
    {
      "property": "Additional_postal_address1",
      "dataitem": [
        {
          "type": 2,
          "item": "1560 30th street"
        }
      ]
    },
    {
      "property": "Additional_postal_code",
      "dataitem": [
        {
          "type": 2,
          "item": "80305"
        }
      ]
    },
    {
      "property": "Additional_state",
      "dataitem": [
        {
          "type": 2,
          "item": "Colorado"
        }
      ]
    },
    {
      "property": "Additional_type_of_contact",
      "dataitem": [
        {
          "type": 2,
          "item": "Technical contact"
        }
      ]
    },
    {
      "property": "Citations",
      "dataitem": [
        {
          "type": 2,
          "item": "480"
        }
      ]
    },
    {
      "property": "City",
      "dataitem": [
        {
          "type": 2,
          "item": "Boulder"
        }
      ]
    },
    {
      "property": "CodeReviewed",
      "dataitem": [
        {
          "type": 2,
          "item": "1"
        }
      ]
    },
    {
      "property": "Code_CMT_compliant_or_not",
      "dataitem": [
        {
          "type": 2,
          "item": "No but possible"
        }
      ]
    },
    {
      "property": "Code_IRF_or_not",
      "dataitem": [
        {
          "type": 2,
          "item": "Yes"
        }
      ]
    },
    {
      "property": "Code_openmi_compliant_or_not",
      "dataitem": [
        {
          "type": 2,
          "item": "No but possible"
        }
      ]
    },
    {
      "property": "Code_optimized",
      "dataitem": [
        {
          "type": 2,
          "item": "Single Processor"
        }
      ]
    },
    {
      "property": "Country",
      "dataitem": [
        {
          "type": 2,
          "item": "United States"
        }
      ]
    },
    {
      "property": "Current_future_collaborators",
      "dataitem": [
        {
          "type": 2,
          "item": "None"
        }
      ]
    },
    {
      "property": "Describe_input_parameters_model",
      "dataitem": [
        {
          "type": 2,
          "item": "Landscape elevation, ELA with time"
        }
      ]
    },
    {
      "property": "Describe_length_scale_and_resolution",
      "dataitem": [
        {
          "type": 2,
          "item": "kilometers"
        }
      ]
    },
    {
      "property": "Describe_output_parameters_model",
      "dataitem": [
        {
          "type": 2,
          "item": "Glacier thickness and elevation"
        }
      ]
    },
    {
      "property": "Describe_processes",
      "dataitem": [
        {
          "type": 2,
          "item": "Glacier growth and evolution"
        }
      ]
    },
    {
      "property": "Describe_time_scale_and_resolution",
      "dataitem": [
        {
          "type": 2,
          "item": "Tens to hundreds of years"
        }
      ]
    },
    {
      "property": "Development_still_active",
      "dataitem": [
        {
          "type": 2,
          "item": "Yes"
        }
      ]
    },
    {
      "property": "Email_address",
      "dataitem": [
        {
          "type": 5,
          "item": "mailto:mark.kessler@colorado.edu"
        }
      ]
    },
    {
      "property": "Extended_model_description",
      "dataitem": [
        {
          "type": 2,
          "item": "Models the growth and evolution of valley glaciers and ice sheets"
        }
      ]
    },
    {
      "property": "First_name",
      "dataitem": [
        {
          "type": 2,
          "item": "Mark"
        }
      ]
    },
    {
      "property": "H-index",
      "dataitem": [
        {
          "type": 1,
          "item": "4"
        }
      ]
    },
    {
      "property": "Input_format_model_other",
      "dataitem": [
        {
          "type": 2,
          "item": "Matlab .mat files"
        }
      ]
    },
    {
      "property": "Institute",
      "dataitem": [
        {
          "type": 2,
          "item": "University of Colorado"
        }
      ]
    },
    {
      "property": "Last_name",
      "dataitem": [
        {
          "type": 2,
          "item": "Kessler"
        }
      ]
    },
    {
      "property": "M-quotient",
      "dataitem": [
        {
          "type": 1,
          "item": "0.15"
        }
      ]
    },
    {
      "property": "Manual_model_available",
      "dataitem": [
        {
          "type": 2,
          "item": "No"
        }
      ]
    },
    {
      "property": "Memory_requirements",
      "dataitem": [
        {
          "type": 2,
          "item": "Minimal"
        }
      ]
    },
    {
      "property": "ModelDomain",
      "dataitem": [
        {
          "type": 2,
          "item": "Terrestrial"
        },
        {
          "type": 2,
          "item": "Cryosphere"
        }
      ]
    },
    {
      "property": "Model_availability",
      "dataitem": [
        {
          "type": 2,
          "item": "As code"
        }
      ]
    },
    {
      "property": "Model_keywords",
      "dataitem": [
        {
          "type": 2,
          "item": "cryosphere"
        }
      ]
    },
    {
      "property": "Model_type",
      "dataitem": [
        {
          "type": 2,
          "item": "Single"
        }
      ]
    },
    {
      "property": "Modelautophrases",
      "dataitem": [
        {
          "type": 2,
          "item": "glacier"
        },
        {
          "type": 2,
          "item": "ice"
        },
        {
          "type": 2,
          "item": "model"
        },
        {
          "type": 2,
          "item": "models the growth"
        },
        {
          "type": 2,
          "item": "ice sheets"
        },
        {
          "type": 2,
          "item": "growth and evolution"
        },
        {
          "type": 2,
          "item": "evolution of valley"
        },
        {
          "type": 2,
          "item": "valley glaciers"
        },
        {
          "type": 2,
          "item": "glaciers and ice"
        },
        {
          "type": 2,
          "item": "models"
        },
        {
          "type": 2,
          "item": "sheets"
        },
        {
          "type": 2,
          "item": "growth"
        },
        {
          "type": 2,
          "item": "evolution"
        },
        {
          "type": 2,
          "item": "valley"
        },
        {
          "type": 2,
          "item": "glaciers"
        },
        {
          "type": 2,
          "item": "cryosphere"
        },
        {
          "type": 2,
          "item": "gc2d"
        }
      ]
    },
    {
      "property": "Nr-of-pubs",
      "dataitem": [
        {
          "type": 2,
          "item": "4"
        }
      ]
    },
    {
      "property": "One-line_model_description",
      "dataitem": [
        {
          "type": 2,
          "item": "Glacier / ice sheet evolution model"
        }
      ]
    },
    {
      "property": "Output_format_model_other",
      "dataitem": [
        {
          "type": 2,
          "item": "Matlab .mat files"
        }
      ]
    },
    {
      "property": "Post_processing_software",
      "dataitem": [
        {
          "type": 4,
          "item": "f"
        }
      ]
    },
    {
      "property": "Postal_address1",
      "dataitem": [
        {
          "type": 2,
          "item": "1560 30th street"
        }
      ]
    },
    {
      "property": "Postal_code",
      "dataitem": [
        {
          "type": 2,
          "item": "80305"
        }
      ]
    },
    {
      "property": "Pre_processing_software",
      "dataitem": [
        {
          "type": 4,
          "item": "f"
        }
      ]
    },
    {
      "property": "Program_license_type",
      "dataitem": [
        {
          "type": 2,
          "item": "Apache public license"
        }
      ]
    },
    {
      "property": "Programming_language",
      "dataitem": [
        {
          "type": 2,
          "item": "Python"
        },
        {
          "type": 2,
          "item": "Matlab"
        }
      ]
    },
    {
      "property": "Run_time_model",
      "dataitem": [
        {
          "type": 2,
          "item": "hours"
        }
      ]
    },
    {
      "property": "Source_code_availability",
      "dataitem": [
        {
          "type": 2,
          "item": "Through CSDMS repository"
        }
      ]
    },
    {
      "property": "Source_csdms_web_address",
      "dataitem": [
        {
          "type": 2,
          "item": "https://github.com/csdms-contrib/gc2d"
        }
      ]
    },
    {
      "property": "Spatial_dimensions",
      "dataitem": [
        {
          "type": 2,
          "item": "2D"
        }
      ]
    },
    {
      "property": "Start_year_development",
      "dataitem": [
        {
          "type": 2,
          "item": "2005"
        }
      ]
    },
    {
      "property": "State",
      "dataitem": [
        {
          "type": 2,
          "item": "Colorado"
        }
      ]
    },
    {
      "property": "Supported_platforms",
      "dataitem": [
        {
          "type": 2,
          "item": "Unix"
        },
        {
          "type": 2,
          "item": "Linux"
        },
        {
          "type": 2,
          "item": "Mac OS"
        },
        {
          "type": 2,
          "item": "Windows"
        }
      ]
    },
    {
      "property": "Type_of_contact",
      "dataitem": [
        {
          "type": 2,
          "item": "Model developer"
        }
      ]
    },
    {
      "property": "Visualization_software_needed",
      "dataitem": [
        {
          "type": 4,
          "item": "f"
        }
      ]
    },
    {
      "property": "_ASK",
      "dataitem": [
        {
          "type": 9,
          "item": "Gc2d#3002##_QUERYf99761521544b5c3f7f7c2caca8dbb1a"
        },
        {
          "type": 9,
          "item": "Gc2d#3002##_QUERY5ed46ed8fe5515a229c5789b2a34c5db"
        },
        {
          "type": 9,
          "item": "Gc2d#3002##_QUERY00b134360b4e67053df2a58b70635315"
        }
      ]
    },
    {
      "property": "_CDAT",
      "dataitem": [
        {
          "type": 6,
          "item": "1/2009/2/17/18/34/33/0"
        }
      ]
    },
    {
      "property": "_INST",
      "dataitem": [
        {
          "type": 9,
          "item": "Pages_using_duplicate_arguments_in_template_calls#14##"
        },
        {
          "type": 9,
          "item": "Models#14##"
        }
      ]
    },
    {
      "property": "_LEDT",
      "dataitem": [
        {
          "type": 9,
          "item": "WikiSysop#2##"
        }
      ]
    },
    {
      "property": "_MDAT",
      "dataitem": [
        {
          "type": 6,
          "item": "1/2020/9/17/2/14/42/0"
        }
      ]
    },
    {
      "property": "_SKEY",
      "dataitem": [
        {
          "type": 2,
          "item": "Gc2d"
        }
      ]
    }
  ],
  "sobj": [
    {
      "subject": "Gc2d#3002##_QUERYf99761521544b5c3f7f7c2caca8dbb1a",
      "data": [
        {
          "property": "_ASKDE",
          "dataitem": [
            {
              "type": 1,
              "item": "0"
            }
          ]
        },
        {
          "property": "_ASKFO",
          "dataitem": [
            {
              "type": 2,
              "item": "plainlist"
            }
          ]
        },
        {
          "property": "_ASKSI",
          "dataitem": [
            {
              "type": 1,
              "item": "1"
            }
          ]
        },
        {
          "property": "_ASKST",
          "dataitem": [
            {
              "type": 2,
              "item": "[[:Model:Gc2d]]"
            }
          ]
        },
        {
          "property": "_SKEY",
          "dataitem": [
            {
              "type": 2,
              "item": "Gc2d# QUERYf99761521544b5c3f7f7c2caca8dbb1a"
            }
          ]
        }
      ]
    },
    {
      "subject": "Gc2d#3002##_QUERY5ed46ed8fe5515a229c5789b2a34c5db",
      "data": [
        {
          "property": "_ASKDE",
          "dataitem": [
            {
              "type": 1,
              "item": "1"
            }
          ]
        },
        {
          "property": "_ASKFO",
          "dataitem": [
            {
              "type": 2,
              "item": "plainlist"
            }
          ]
        },
        {
          "property": "_ASKSI",
          "dataitem": [
            {
              "type": 1,
              "item": "5"
            }
          ]
        },
        {
          "property": "_ASKST",
          "dataitem": [
            {
              "type": 2,
              "item": "[[User:+]] [[First name member::Mark]] [[Last name member::Kessler]]"
            }
          ]
        },
        {
          "property": "_SKEY",
          "dataitem": [
            {
              "type": 2,
              "item": "Gc2d# QUERY5ed46ed8fe5515a229c5789b2a34c5db"
            }
          ]
        }
      ]
    },
    {
      "subject": "Gc2d#3002##_QUERY00b134360b4e67053df2a58b70635315",
      "data": [
        {
          "property": "_ASKDE",
          "dataitem": [
            {
              "type": 1,
              "item": "1"
            }
          ]
        },
        {
          "property": "_ASKFO",
          "dataitem": [
            {
              "type": 2,
              "item": "ul"
            }
          ]
        },
        {
          "property": "_ASKSI",
          "dataitem": [
            {
              "type": 1,
              "item": "5"
            }
          ]
        },
        {
          "property": "_ASKST",
          "dataitem": [
            {
              "type": 2,
              "item": "[[Model:+]] [[First name::Mark]] [[Last name::Kessler]]"
            }
          ]
        },
        {
          "property": "_SKEY",
          "dataitem": [
            {
              "type": 2,
              "item": "Gc2d# QUERY00b134360b4e67053df2a58b70635315"
            }
          ]
        }
      ]
    }
  ],
  "serializer": "SMW\\Serializers\\SemanticDataSerializer",
  "version": 2
}